declargs/__init__.py
declargs/declargs.py
declargs/dummy-config.yaml
declargs/dummy-schema.yaml
declargs/dummy.yaml
declargs/my-app.py
declargs/simple.py
declargs-0.1.0.dist-info/LICENSE
declargs-0.1.0.dist-info/WHEEL
declargs-0.1.0.dist-info/METADATA
declargs-0.1.0.dist-info/RECORD
